pycryptobox/__init__.py
pycryptobox/decryption.py
pycryptobox/encryption.py
pycryptobox-1.0.5.dist-info/METADATA
pycryptobox-1.0.5.dist-info/WHEEL
pycryptobox-1.0.5.dist-info/entry_points.txt
pycryptobox-1.0.5.dist-info/top_level.txt
pycryptobox-1.0.5.dist-info/RECORD
