Metadata-Version: 2.1
Name: pycryptobox
Version: 1.0.5
Summary: A package for encrypting and decrypting files
Home-page: https://github.com/LpCodes/pycryptobox
Author: https://github.com/LpCodes
Keywords: encryption decryption file-security cryptography
Classifier: Development Status :: 3 - Alpha
Classifier: Intended Audience :: Developers
Classifier: License :: OSI Approved :: MIT License
Classifier: Programming Language :: Python :: 3
Classifier: Programming Language :: Python :: 3.6
Classifier: Programming Language :: Python :: 3.7
Classifier: Programming Language :: Python :: 3.8
Classifier: Programming Language :: Python :: 3.9
Classifier: Programming Language :: Python :: 3 :: Only
Classifier: Topic :: Security :: Cryptography
Classifier: Topic :: System :: Archiving :: Compression
Requires-Dist: pyAesCrypt (==6.0.0)
Requires-Dist: python-dotenv
